DeepCache/__init__.py
DeepCache/flops.py
DeepCache/extension/__init__.py
DeepCache/extension/deepcache.py
DeepCache/sd/__init__.py
DeepCache/sd/pipeline_stable_diffusion.py
DeepCache/sd/pipeline_text_to_video_zero.py
DeepCache/sd/pipeline_utils.py
DeepCache/sd/unet_2d_blocks.py
DeepCache/sd/unet_2d_condition.py
DeepCache/sdxl/__init__.py
DeepCache/sdxl/pipeline_stable_diffusion_xl.py
DeepCache/sdxl/pipeline_stable_diffusion_xl_img2img.py
DeepCache/sdxl/pipeline_utils.py
DeepCache/sdxl/unet_2d_blocks.py
DeepCache/sdxl/unet_2d_condition.py
DeepCache/svd/__init__.py
DeepCache/svd/pipeline_stable_video_diffusion.py
DeepCache/svd/pipeline_utils.py
DeepCache/svd/unet_3d_blocks.py
DeepCache/svd/unet_spatio_temporal_condition.py
DeepCache-0.1.1.dist-info/LICENSE
DeepCache-0.1.1.dist-info/METADATA
DeepCache-0.1.1.dist-info/WHEEL
DeepCache-0.1.1.dist-info/top_level.txt
DeepCache-0.1.1.dist-info/RECORD
