Metadata-Version: 2.1
Name: DeepCache
Version: 0.1.1
Summary: DeepCache: Accelerating Diffusion Models for Free
Home-page: https://github.com/horseee/DeepCache
Author: Xinyin Ma
Author-email: maxinyin@u.nus.edu
Classifier: Programming Language :: Python :: 3
Classifier: License :: OSI Approved :: Apache Software License
Classifier: Operating System :: OS Independent
Requires-Python: >=3.6
License-File: LICENSE
Requires-Dist: torch
Requires-Dist: diffusers
Requires-Dist: transformers
